heiko/__init__.py
heiko/cli.py
heiko/config.py
heiko/daemon.py
heiko/load_utils.py
heiko/logging
heiko/main.py
heiko/schedulers.py
heiko/ssh_utils.py
heiko/utils/__init__.py
heiko/utils/load.py
heiko/utils/ssh.py
py_heiko-0.0.1.dist-info/LICENSE
py_heiko-0.0.1.dist-info/METADATA
py_heiko-0.0.1.dist-info/WHEEL
py_heiko-0.0.1.dist-info/entry_points.txt
py_heiko-0.0.1.dist-info/top_level.txt
py_heiko-0.0.1.dist-info/RECORD
