Metadata-Version: 2.1
Name: py-heiko
Version: 0.0.1
Summary: A fancy load balancer for light weight devices
Home-page: https://github.com/psiayn/heiko
Author: Pranav Kesavarapu
Author-email: pranavkesavarapu@gmail.com
License: UNKNOWN
Platform: UNKNOWN
Classifier: Programming Language :: Python :: 3
Classifier: License :: OSI Approved :: Apache Software License
Classifier: Operating System :: OS Independent
Requires-Python: >=3.7
Requires-Dist: asyncssh (>=2.4.0)
Requires-Dist: PyYAML (>=5.3.0)
